syncline_mcp_server/__init__.py
syncline_mcp_server/server.py
syncline_mcp_server-1.0.30.dist-info/METADATA
syncline_mcp_server-1.0.30.dist-info/WHEEL
syncline_mcp_server-1.0.30.dist-info/entry_points.txt
syncline_mcp_server-1.0.30.dist-info/top_level.txt
syncline_mcp_server-1.0.30.dist-info/RECORD
