Metadata-Version: 2.4
Name: syncline-mcp-server
Version: 1.0.30
Summary: Model Context Protocol server for Syncline - AI-powered meeting scheduling
Author-email: Kekwanu Labs <hello@kekwanulabs.com>
License: MIT
Project-URL: Homepage, https://syncline.run
Project-URL: Documentation, https://kekwanulabslllc.mintlify.app
Project-URL: Repository, https://github.com/KekwanuLabs/syncline
Project-URL: Bug Tracker, https://github.com/KekwanuLabs/syncline/issues
Keywords: mcp,model-context-protocol,syncline,scheduling,ai,calendar
Classifier: Development Status :: 4 - Beta
Classifier: Intended Audience :: Developers
Classifier: License :: OSI Approved :: MIT License
Classifier: Programming Language :: Python :: 3
Classifier: Programming Language :: Python :: 3.10
Classifier: Programming Language :: Python :: 3.11
Classifier: Programming Language :: Python :: 3.12
Requires-Python: >=3.10
Requires-Dist: mcp>=1.0.0
Requires-Dist: httpx>=0.27.0
